genoforge/__init__.py
genoforge/fitness.py
genoforge-0.0.3.dist-info/LICENSE
genoforge-0.0.3.dist-info/METADATA
genoforge-0.0.3.dist-info/WHEEL
genoforge-0.0.3.dist-info/top_level.txt
genoforge-0.0.3.dist-info/RECORD
