Metadata-Version: 2.1
Name: genoforge
Version: 0.0.3
Home-page: https://github.com/Jorgelzn/Genoforge
Author: Jorge Lizcano
Author-email: jorgelizgo@gmail.com
License-File: LICENSE
Requires-Dist: numpy
